odoo/addons/product_kardex/LICENSE
odoo/addons/product_kardex/README.rst
odoo/addons/product_kardex/__init__.py
odoo/addons/product_kardex/__manifest__.py
odoo/addons/product_kardex/demo/document_demo.xml
odoo/addons/product_kardex/images/screen.png
odoo/addons/product_kardex/models/__init__.py
odoo/addons/product_kardex/models/product_product.py
odoo/addons/product_kardex/models/product_template.py
odoo/addons/product_kardex/security/ir.model.access.csv
odoo/addons/product_kardex/static/description/icon.png
odoo/addons/product_kardex/static/description/index.html
odoo/addons/product_kardex/static/src/css/style.css
odoo/addons/product_kardex/static/src/xml/sync_action.xml
odoo/addons/product_kardex/views/product_kardex_views.xml
odoo_addon_product_kardex-18.0.1.0.0.dist-info/METADATA
odoo_addon_product_kardex-18.0.1.0.0.dist-info/WHEEL
odoo_addon_product_kardex-18.0.1.0.0.dist-info/top_level.txt
odoo_addon_product_kardex-18.0.1.0.0.dist-info/RECORD
